jif/__init__.py
jif/__main__.py
jif/versionbump.py
jif-3.0.2.dist-info/entry_points.txt
jif-3.0.2.dist-info/LICENSE.txt
jif-3.0.2.dist-info/WHEEL
jif-3.0.2.dist-info/METADATA
jif-3.0.2.dist-info/RECORD
