Metadata-Version: 2.1
Name: jif
Version: 3.0.2
Summary: 
Author: Jason Atallah
Author-email: jason.atallah@gmail.com
Requires-Python: >=3.9,<4.0
Classifier: Programming Language :: Python :: 3
Classifier: Programming Language :: Python :: 3.10
Classifier: Programming Language :: Python :: 3.9
Requires-Dist: PyYAML (>=6.0,<7.0)
Requires-Dist: typer (>=0.6.1,<0.7.0)
